<?xml version="1.0" encoding="UTF-8"?>
<typeSystemDescription xmlns="http://uima.apache.org/resourceSpecifier">
  <name>Dependency</name>
  <description/>
  <version>1.0</version>
  <vendor/>
  <imports>
    <import name="desc.type.LexicalUnits"/>
  </imports>
  <types>
    <typeDescription>
      <name>de.tudarmstadt.ukp.dkpro.core.api.syntax.type.dependency.Dependency</name>
      <description/>
      <supertypeName>uima.tcas.Annotation</supertypeName>
      <features>
        <featureDescription>
          <name>Governor</name>
          <description>The governor word</description>
          <rangeTypeName>de.tudarmstadt.ukp.dkpro.core.api.segmentation.type.Token</rangeTypeName>
        </featureDescription>
        <featureDescription>
          <name>Dependent</name>
          <description>The dependent word</description>
          <rangeTypeName>de.tudarmstadt.ukp.dkpro.core.api.segmentation.type.Token</rangeTypeName>
        </featureDescription>
        <featureDescription>
          <name>DependencyType</name>
          <description>The dependency type</description>
          <rangeTypeName>uima.cas.String</rangeTypeName>
        </featureDescription>
      </features>
    </typeDescription>
    <typeDescription>
      <name>de.tudarmstadt.ukp.dkpro.core.api.syntax.type.dependency.NSUBJ</name>
      <description/>
      <supertypeName>de.tudarmstadt.ukp.dkpro.core.api.syntax.type.dependency.Dependency</supertypeName>
    </typeDescription>
    <typeDescription>
      <name>de.tudarmstadt.ukp.dkpro.core.api.syntax.type.dependency.AMOD</name>
      <description/>
      <supertypeName>de.tudarmstadt.ukp.dkpro.core.api.syntax.type.dependency.Dependency</supertypeName>
    </typeDescription>
    <typeDescription>
      <name>de.tudarmstadt.ukp.dkpro.core.api.syntax.type.dependency.DEP</name>
      <description/>
      <supertypeName>de.tudarmstadt.ukp.dkpro.core.api.syntax.type.dependency.Dependency</supertypeName>
    </typeDescription>
    <typeDescription>
      <name>de.tudarmstadt.ukp.dkpro.core.api.syntax.type.dependency.DET</name>
      <description/>
      <supertypeName>de.tudarmstadt.ukp.dkpro.core.api.syntax.type.dependency.Dependency</supertypeName>
    </typeDescription>
    <typeDescription>
      <name>de.tudarmstadt.ukp.dkpro.core.api.syntax.type.dependency.POBJ</name>
      <description/>
      <supertypeName>de.tudarmstadt.ukp.dkpro.core.api.syntax.type.dependency.Dependency</supertypeName>
    </typeDescription>
    <typeDescription>
      <name>de.tudarmstadt.ukp.dkpro.core.api.syntax.type.dependency.PREP</name>
      <description/>
      <supertypeName>de.tudarmstadt.ukp.dkpro.core.api.syntax.type.dependency.Dependency</supertypeName>
    </typeDescription>
    <typeDescription>
      <name>de.tudarmstadt.ukp.dkpro.core.api.syntax.type.dependency.CC</name>
      <description/>
      <supertypeName>de.tudarmstadt.ukp.dkpro.core.api.syntax.type.dependency.Dependency</supertypeName>
    </typeDescription>
    <typeDescription>
      <name>de.tudarmstadt.ukp.dkpro.core.api.syntax.type.dependency.CONJ</name>
      <description/>
      <supertypeName>de.tudarmstadt.ukp.dkpro.core.api.syntax.type.dependency.Dependency</supertypeName>
    </typeDescription>
    <typeDescription>
      <name>de.tudarmstadt.ukp.dkpro.core.api.syntax.type.dependency.NN</name>
      <description/>
      <supertypeName>de.tudarmstadt.ukp.dkpro.core.api.syntax.type.dependency.Dependency</supertypeName>
    </typeDescription>
    <typeDescription>
      <name>de.tudarmstadt.ukp.dkpro.core.api.syntax.type.dependency.NUM</name>
      <description/>
      <supertypeName>de.tudarmstadt.ukp.dkpro.core.api.syntax.type.dependency.Dependency</supertypeName>
    </typeDescription>
    <typeDescription>
      <name>de.tudarmstadt.ukp.dkpro.core.api.syntax.type.dependency.CCOMP</name>
      <description/>
      <supertypeName>de.tudarmstadt.ukp.dkpro.core.api.syntax.type.dependency.Dependency</supertypeName>
    </typeDescription>
    <typeDescription>
      <name>de.tudarmstadt.ukp.dkpro.core.api.syntax.type.dependency.NUMBER</name>
      <description/>
      <supertypeName>de.tudarmstadt.ukp.dkpro.core.api.syntax.type.dependency.Dependency</supertypeName>
    </typeDescription>
    <typeDescription>
      <name>de.tudarmstadt.ukp.dkpro.core.api.syntax.type.dependency.CONJ_YET</name>
      <description/>
      <supertypeName>de.tudarmstadt.ukp.dkpro.core.api.syntax.type.dependency.Dependency</supertypeName>
    </typeDescription>
    <typeDescription>
      <name>de.tudarmstadt.ukp.dkpro.core.api.syntax.type.dependency.COP</name>
      <description/>
      <supertypeName>de.tudarmstadt.ukp.dkpro.core.api.syntax.type.dependency.Dependency</supertypeName>
    </typeDescription>
    <typeDescription>
      <name>de.tudarmstadt.ukp.dkpro.core.api.syntax.type.dependency.ADVMOD</name>
      <description/>
      <supertypeName>de.tudarmstadt.ukp.dkpro.core.api.syntax.type.dependency.Dependency</supertypeName>
    </typeDescription>
    <typeDescription>
      <name>de.tudarmstadt.ukp.dkpro.core.api.syntax.type.dependency.COMPLM</name>
      <description/>
      <supertypeName>de.tudarmstadt.ukp.dkpro.core.api.syntax.type.dependency.Dependency</supertypeName>
    </typeDescription>
    <typeDescription>
      <name>de.tudarmstadt.ukp.dkpro.core.api.syntax.type.dependency.AUX0</name>
      <description/>
      <supertypeName>de.tudarmstadt.ukp.dkpro.core.api.syntax.type.dependency.Dependency</supertypeName>
    </typeDescription>
    <typeDescription>
      <name>de.tudarmstadt.ukp.dkpro.core.api.syntax.type.dependency.XCOMP</name>
      <description/>
      <supertypeName>de.tudarmstadt.ukp.dkpro.core.api.syntax.type.dependency.Dependency</supertypeName>
    </typeDescription>
    <typeDescription>
      <name>de.tudarmstadt.ukp.dkpro.core.api.syntax.type.dependency.POSS</name>
      <description/>
      <supertypeName>de.tudarmstadt.ukp.dkpro.core.api.syntax.type.dependency.Dependency</supertypeName>
    </typeDescription>
    <typeDescription>
      <name>de.tudarmstadt.ukp.dkpro.core.api.syntax.type.dependency.DOBJ</name>
      <description/>
      <supertypeName>de.tudarmstadt.ukp.dkpro.core.api.syntax.type.dependency.Dependency</supertypeName>
    </typeDescription>
    <typeDescription>
      <name>de.tudarmstadt.ukp.dkpro.core.api.syntax.type.dependency.AUXPASS</name>
      <description/>
      <supertypeName>de.tudarmstadt.ukp.dkpro.core.api.syntax.type.dependency.Dependency</supertypeName>
    </typeDescription>
    <typeDescription>
      <name>de.tudarmstadt.ukp.dkpro.core.api.syntax.type.dependency.RCMOD</name>
      <description/>
      <supertypeName>de.tudarmstadt.ukp.dkpro.core.api.syntax.type.dependency.Dependency</supertypeName>
    </typeDescription>
    <typeDescription>
      <name>de.tudarmstadt.ukp.dkpro.core.api.syntax.type.dependency.AGENT</name>
      <description/>
      <supertypeName>de.tudarmstadt.ukp.dkpro.core.api.syntax.type.dependency.Dependency</supertypeName>
    </typeDescription>
    <typeDescription>
      <name>de.tudarmstadt.ukp.dkpro.core.api.syntax.type.dependency.APPOS</name>
      <description/>
      <supertypeName>de.tudarmstadt.ukp.dkpro.core.api.syntax.type.dependency.Dependency</supertypeName>
    </typeDescription>
    <typeDescription>
      <name>de.tudarmstadt.ukp.dkpro.core.api.syntax.type.dependency.TMOD</name>
      <description/>
      <supertypeName>de.tudarmstadt.ukp.dkpro.core.api.syntax.type.dependency.Dependency</supertypeName>
    </typeDescription>
    <typeDescription>
      <name>de.tudarmstadt.ukp.dkpro.core.api.syntax.type.dependency.PARTMOD</name>
      <description/>
      <supertypeName>de.tudarmstadt.ukp.dkpro.core.api.syntax.type.dependency.Dependency</supertypeName>
    </typeDescription>
    <typeDescription>
      <name>de.tudarmstadt.ukp.dkpro.core.api.syntax.type.dependency.MEASURE</name>
      <description/>
      <supertypeName>de.tudarmstadt.ukp.dkpro.core.api.syntax.type.dependency.Dependency</supertypeName>
    </typeDescription>
    <typeDescription>
      <name>de.tudarmstadt.ukp.dkpro.core.api.syntax.type.dependency.ACOMP</name>
      <description/>
      <supertypeName>de.tudarmstadt.ukp.dkpro.core.api.syntax.type.dependency.Dependency</supertypeName>
    </typeDescription>
    <typeDescription>
      <name>de.tudarmstadt.ukp.dkpro.core.api.syntax.type.dependency.PREDET</name>
      <description/>
      <supertypeName>de.tudarmstadt.ukp.dkpro.core.api.syntax.type.dependency.Dependency</supertypeName>
    </typeDescription>
    <typeDescription>
      <name>de.tudarmstadt.ukp.dkpro.core.api.syntax.type.dependency.MARK</name>
      <description/>
      <supertypeName>de.tudarmstadt.ukp.dkpro.core.api.syntax.type.dependency.Dependency</supertypeName>
    </typeDescription>
    <typeDescription>
      <name>de.tudarmstadt.ukp.dkpro.core.api.syntax.type.dependency.ADVCL</name>
      <description/>
      <supertypeName>de.tudarmstadt.ukp.dkpro.core.api.syntax.type.dependency.Dependency</supertypeName>
    </typeDescription>
    <typeDescription>
      <name>de.tudarmstadt.ukp.dkpro.core.api.syntax.type.dependency.NEG</name>
      <description/>
      <supertypeName>de.tudarmstadt.ukp.dkpro.core.api.syntax.type.dependency.Dependency</supertypeName>
    </typeDescription>
    <typeDescription>
      <name>de.tudarmstadt.ukp.dkpro.core.api.syntax.type.dependency.NSUBJPASS</name>
      <description/>
      <supertypeName>de.tudarmstadt.ukp.dkpro.core.api.syntax.type.dependency.Dependency</supertypeName>
    </typeDescription>
    <typeDescription>
      <name>de.tudarmstadt.ukp.dkpro.core.api.syntax.type.dependency.PREPC</name>
      <description/>
      <supertypeName>de.tudarmstadt.ukp.dkpro.core.api.syntax.type.dependency.Dependency</supertypeName>
    </typeDescription>
    <typeDescription>
      <name>de.tudarmstadt.ukp.dkpro.core.api.syntax.type.dependency.QUANTMOD</name>
      <description/>
      <supertypeName>de.tudarmstadt.ukp.dkpro.core.api.syntax.type.dependency.Dependency</supertypeName>
    </typeDescription>
    <typeDescription>
      <name>de.tudarmstadt.ukp.dkpro.core.api.syntax.type.dependency.CSUBJPASS</name>
      <description/>
      <supertypeName>de.tudarmstadt.ukp.dkpro.core.api.syntax.type.dependency.Dependency</supertypeName>
    </typeDescription>
    <typeDescription>
      <name>de.tudarmstadt.ukp.dkpro.core.api.syntax.type.dependency.CSUBJ</name>
      <description/>
      <supertypeName>de.tudarmstadt.ukp.dkpro.core.api.syntax.type.dependency.Dependency</supertypeName>
    </typeDescription>
    <typeDescription>
      <name>de.tudarmstadt.ukp.dkpro.core.api.syntax.type.dependency.REL</name>
      <description/>
      <supertypeName>de.tudarmstadt.ukp.dkpro.core.api.syntax.type.dependency.Dependency</supertypeName>
    </typeDescription>
    <typeDescription>
      <name>de.tudarmstadt.ukp.dkpro.core.api.syntax.type.dependency.PRT</name>
      <description/>
      <supertypeName>de.tudarmstadt.ukp.dkpro.core.api.syntax.type.dependency.Dependency</supertypeName>
    </typeDescription>
    <typeDescription>
      <name>de.tudarmstadt.ukp.dkpro.core.api.syntax.type.dependency.PUNCT</name>
      <description/>
      <supertypeName>de.tudarmstadt.ukp.dkpro.core.api.syntax.type.dependency.Dependency</supertypeName>
    </typeDescription>
    <typeDescription>
      <name>de.tudarmstadt.ukp.dkpro.core.api.syntax.type.dependency.PCOMP</name>
      <description/>
      <supertypeName>de.tudarmstadt.ukp.dkpro.core.api.syntax.type.dependency.Dependency</supertypeName>
    </typeDescription>
    <typeDescription>
      <name>de.tudarmstadt.ukp.dkpro.core.api.syntax.type.dependency.XCOMP</name>
      <description/>
      <supertypeName>de.tudarmstadt.ukp.dkpro.core.api.syntax.type.dependency.Dependency</supertypeName>
    </typeDescription>
    <typeDescription>
      <name>de.tudarmstadt.ukp.dkpro.core.api.syntax.type.dependency.EXPL</name>
      <description/>
      <supertypeName>de.tudarmstadt.ukp.dkpro.core.api.syntax.type.dependency.Dependency</supertypeName>
    </typeDescription>
    <typeDescription>
      <name>de.tudarmstadt.ukp.dkpro.core.api.syntax.type.dependency.INFMOD</name>
      <description/>
      <supertypeName>de.tudarmstadt.ukp.dkpro.core.api.syntax.type.dependency.Dependency</supertypeName>
    </typeDescription>
    <typeDescription>
      <name>de.tudarmstadt.ukp.dkpro.core.api.syntax.type.dependency.CSUBJPASS</name>
      <description/>
      <supertypeName>de.tudarmstadt.ukp.dkpro.core.api.syntax.type.dependency.Dependency</supertypeName>
    </typeDescription>
    <typeDescription>
      <name>de.tudarmstadt.ukp.dkpro.core.api.syntax.type.dependency.ATTR</name>
      <description/>
      <supertypeName>de.tudarmstadt.ukp.dkpro.core.api.syntax.type.dependency.Dependency</supertypeName>
    </typeDescription>
    <typeDescription>
      <name>de.tudarmstadt.ukp.dkpro.core.api.syntax.type.dependency.IOBJ</name>
      <description/>
      <supertypeName>de.tudarmstadt.ukp.dkpro.core.api.syntax.type.dependency.Dependency</supertypeName>
    </typeDescription>
    <typeDescription>
      <name>de.tudarmstadt.ukp.dkpro.core.api.syntax.type.dependency.CONJP</name>
      <description/>
      <supertypeName>de.tudarmstadt.ukp.dkpro.core.api.syntax.type.dependency.Dependency</supertypeName>
    </typeDescription>
    <typeDescription>
      <name>de.tudarmstadt.ukp.dkpro.core.api.syntax.type.dependency.PRECONJ</name>
      <description/>
      <supertypeName>de.tudarmstadt.ukp.dkpro.core.api.syntax.type.dependency.Dependency</supertypeName>
    </typeDescription>
    <typeDescription>
      <name>de.tudarmstadt.ukp.dkpro.core.api.syntax.type.dependency.PURPCL</name>
      <description/>
      <supertypeName>de.tudarmstadt.ukp.dkpro.core.api.syntax.type.dependency.Dependency</supertypeName>
    </typeDescription>
    <typeDescription>
      <name>de.tudarmstadt.ukp.dkpro.core.api.syntax.type.dependency.PRED</name>
      <description/>
      <supertypeName>de.tudarmstadt.ukp.dkpro.core.api.syntax.type.dependency.Dependency</supertypeName>
    </typeDescription>
    <typeDescription>
      <name>de.tudarmstadt.ukp.dkpro.core.api.syntax.type.dependency.PARATAXIS</name>
      <description/>
      <supertypeName>de.tudarmstadt.ukp.dkpro.core.api.syntax.type.dependency.Dependency</supertypeName>
    </typeDescription>
    <typeDescription>
      <name>de.tudarmstadt.ukp.dkpro.core.api.syntax.type.dependency.ABBREV</name>
      <description/>
      <supertypeName>de.tudarmstadt.ukp.dkpro.core.api.syntax.type.dependency.Dependency</supertypeName>
    </typeDescription>
    <typeDescription>
      <name>de.tudarmstadt.ukp.dkpro.core.api.syntax.type.dependency.POSSESSIVE</name>
      <description/>
      <supertypeName>de.tudarmstadt.ukp.dkpro.core.api.syntax.type.dependency.Dependency</supertypeName>
    </typeDescription>
    <typeDescription>
      <name>de.tudarmstadt.ukp.dkpro.core.api.syntax.type.dependency.Governor</name>
      <description/>
      <supertypeName>uima.tcas.Annotation</supertypeName>
      <features>
        <featureDescription>
          <name>Dependent</name>
          <description/>
          <rangeTypeName>de.tudarmstadt.ukp.dkpro.core.api.segmentation.type.Token</rangeTypeName>
        </featureDescription>
        <featureDescription>
          <name>Dependency</name>
          <description/>
          <rangeTypeName>de.tudarmstadt.ukp.dkpro.core.api.syntax.type.dependency.Dependency</rangeTypeName>
        </featureDescription>
      </features>
    </typeDescription>
    <typeDescription>
      <name>de.tudarmstadt.ukp.dkpro.core.api.syntax.type.dependency.Dependent</name>
      <description/>
      <supertypeName>uima.tcas.Annotation</supertypeName>
      <features>
        <featureDescription>
          <name>Governor</name>
          <description/>
          <rangeTypeName>de.tudarmstadt.ukp.dkpro.core.api.segmentation.type.Token</rangeTypeName>
        </featureDescription>
        <featureDescription>
          <name>Dependency</name>
          <description/>
          <rangeTypeName>de.tudarmstadt.ukp.dkpro.core.api.syntax.type.dependency.Dependency</rangeTypeName>
        </featureDescription>
      </features>
    </typeDescription>
    <typeDescription>
      <name>de.tudarmstadt.ukp.dkpro.core.api.syntax.type.dependency.NPADVMOD</name>
      <description/>
      <supertypeName>de.tudarmstadt.ukp.dkpro.core.api.syntax.type.dependency.Dependency</supertypeName>
    </typeDescription>
    <typeDescription>
      <name>de.tudarmstadt.ukp.dkpro.core.api.syntax.type.dependency.XSUBJ</name>
      <description/>
      <supertypeName>de.tudarmstadt.ukp.dkpro.core.api.syntax.type.dependency.Dependency</supertypeName>
    </typeDescription>
    <typeDescription>
      <name>de.tudarmstadt.ukp.dkpro.core.api.syntax.type.dependency.MWE</name>
      <description/>
      <supertypeName>de.tudarmstadt.ukp.dkpro.core.api.syntax.type.dependency.Dependency</supertypeName>
    </typeDescription>
    <typeDescription>
      <name>de.tudarmstadt.ukp.dkpro.core.api.syntax.type.dependency.REF</name>
      <description/>
      <supertypeName>de.tudarmstadt.ukp.dkpro.core.api.syntax.type.dependency.Dependency</supertypeName>
    </typeDescription>
  </types>
</typeSystemDescription>
